run_isolated/__init__.py
run_isolated/defs.py
run_isolated/py.typed
run_isolated/rdocker.py
run_isolated/util.py
run_isolated-0.1.1.dist-info/METADATA
run_isolated-0.1.1.dist-info/WHEEL
run_isolated-0.1.1.dist-info/RECORD
