Metadata-Version: 2.4
Name: run-isolated
Version: 0.1.1
Summary: Run commands in an isolated environment, e.g. a Docker container
Project-URL: Homepage, https://devel.ringlet.net/sysutils/run-isolated/
Project-URL: Changes, https://devel.ringlet.net/sysutils/run-isolated/changes/
Project-URL: Issue Tracker, https://gitlab.com/ppentchev/run-isolated/-/issues
Project-URL: Source Code, https://gitlab.com/ppentchev/run-isolated
Author-email: Peter Pentchev <roam@ringlet.net>
License: BSD-2-Clause
Classifier: Development Status :: 5 - Production/Stable
Classifier: Intended Audience :: Developers
Classifier: License :: DFSG approved
Classifier: License :: Freely Distributable
Classifier: License :: OSI Approved :: BSD License
Classifier: Operating System :: OS Independent
Classifier: Programming Language :: Python
Classifier: Programming Language :: Python :: 3
Classifier: Programming Language :: Python :: 3 :: Only
Classifier: Programming Language :: Python :: 3.11
Classifier: Programming Language :: Python :: 3.12
Classifier: Programming Language :: Python :: 3.13
Classifier: Programming Language :: Python :: 3.14
Classifier: Topic :: Software Development :: Libraries
Classifier: Topic :: Software Development :: Libraries :: Python Modules
Classifier: Topic :: Software Development :: Testing
Classifier: Topic :: Software Development :: Testing :: Unit
Classifier: Typing :: Typed
Requires-Python: >=3.11
Requires-Dist: pshlex<0.2,>=0.1
